urlman/__init__.py
urlman/serializers.py
urlman-2.0.2.dist-info/LICENSE
urlman-2.0.2.dist-info/METADATA
urlman-2.0.2.dist-info/WHEEL
urlman-2.0.2.dist-info/top_level.txt
urlman-2.0.2.dist-info/RECORD
